Knapsack.py
Player.py
runKnap.py
KnapKings-0.0.1.dist-info/LICENSE.txt
KnapKings-0.0.1.dist-info/METADATA
KnapKings-0.0.1.dist-info/WHEEL
KnapKings-0.0.1.dist-info/top_level.txt
KnapKings-0.0.1.dist-info/RECORD
